bolinette/core/README.md
bolinette/core/__init__.py
bolinette/core/__main__.py
bolinette/core/bolinette.py
bolinette/core/cache.py
bolinette/core/command/__init__.py
bolinette/core/command/command.py
bolinette/core/command/debug.py
bolinette/core/command/parser.py
bolinette/core/environment/__init__.py
bolinette/core/environment/env.py
bolinette/core/environment/sections.py
bolinette/core/exceptions.py
bolinette/core/expressions/__init__.py
bolinette/core/expressions/exceptions.py
bolinette/core/expressions/nodes.py
bolinette/core/expressions/tree.py
bolinette/core/extension.py
bolinette/core/injection/__init__.py
bolinette/core/injection/context.py
bolinette/core/injection/decorators.py
bolinette/core/injection/hook.py
bolinette/core/injection/injection.py
bolinette/core/injection/pool.py
bolinette/core/injection/registration.py
bolinette/core/injection/resolver.py
bolinette/core/logging.py
bolinette/core/mapping/__init__.py
bolinette/core/mapping/exceptions.py
bolinette/core/mapping/json.py
bolinette/core/mapping/mapper.py
bolinette/core/mapping/profiles.py
bolinette/core/mapping/sequence.py
bolinette/core/metadata.py
bolinette/core/objects.py
bolinette/core/py.typed
bolinette/core/pyproject.toml
bolinette/core/startup.py
bolinette/core/testing.py
bolinette/core/types/__init__.py
bolinette/core/types/checker.py
bolinette/core/types/function.py
bolinette/core/types/lookup.py
bolinette/core/types/type.py
bolinette/core/types/type_collection.py
bolinette/core/utils/__init__.py
bolinette/core/utils/attrs.py
bolinette/core/utils/collections.py
bolinette/core/utils/strings.py
bolinette-0.18.2.dist-info/LICENSE.txt
bolinette-0.18.2.dist-info/METADATA
bolinette-0.18.2.dist-info/WHEEL
bolinette-0.18.2.dist-info/entry_points.txt
bolinette-0.18.2.dist-info/RECORD
